{
  "meta": {
    "engine": "rcpp",
    "T_per_exporter": 1000000,
    "seed": 20260717,
    "quick": false,
    "git_rev": "4a947c0",
    "timestamp": "2026-07-21T00:59:00-0400"
  },
  "tolerances": {
    "tol_A": 0.02,
    "power_mult": 5,
    "tol_B": 0.05,
    "tol_C": 0.05,
    "tol_D": 0.02,
    "tol_E": 0.05
  },
  "eq11_signs": "corrected (G1, v0.4.1); Test D negative control is the printed equation",
  "test_A": {
    "grid": [
      {
        "sigma": 2,
        "gam_k": 0.3,
        "resid_ratio_true": 0.00281198,
        "resid_ratio_perturbed": 0.48577613
      },
      {
        "sigma": 3,
        "gam_k": 0.3,
        "resid_ratio_true": 0.00170831,
        "resid_ratio_perturbed": 0.2354516
      },
      {
        "sigma": 5,
        "gam_k": 0.3,
        "resid_ratio_true": 0.00106008,
        "resid_ratio_perturbed": 0.13776453
      },
      {
        "sigma": 2,
        "gam_k": 0.7,
        "resid_ratio_true": 0.00206044,
        "resid_ratio_perturbed": 0.21141888
      },
      {
        "sigma": 3,
        "gam_k": 0.7,
        "resid_ratio_true": 0.00215161,
        "resid_ratio_perturbed": 0.13325583
      },
      {
        "sigma": 5,
        "gam_k": 0.7,
        "resid_ratio_true": 0.00186242,
        "resid_ratio_perturbed": 0.11043381
      },
      {
        "sigma": 2,
        "gam_k": 1.5,
        "resid_ratio_true": 0.0017773,
        "resid_ratio_perturbed": 0.11016973
      },
      {
        "sigma": 3,
        "gam_k": 1.5,
        "resid_ratio_true": 0.00234626,
        "resid_ratio_perturbed": 0.08116596
      },
      {
        "sigma": 5,
        "gam_k": 1.5,
        "resid_ratio_true": 0.00201829,
        "resid_ratio_perturbed": 0.07332196
      }
    ],
    "pass_truth": true,
    "pass_power": true
  },
  "test_B": {
    "median_abs_bias": 0.00163517,
    "pass": true
  },
  "test_C": {
    "gam_k_hat": 0.70152064,
    "gam_k_true": 0.7,
    "median_abs_bias_j": 0.00173448,
    "convergence": 0,
    "pass": true
  },
  "test_D": {
    "grid": [
      {
        "sigma": 2.5,
        "sigma_V": 3,
        "gam_V": 0.9,
        "resid_ratio_true": 0.00177047,
        "resid_ratio_printed": 0.48195915
      },
      {
        "sigma": 4,
        "sigma_V": 3,
        "gam_V": 0.9,
        "resid_ratio_true": 0.00107142,
        "resid_ratio_printed": 0.2795597
      },
      {
        "sigma": 2.5,
        "sigma_V": 5,
        "gam_V": 0.9,
        "resid_ratio_true": 0.00061269,
        "resid_ratio_printed": 1.77150727
      },
      {
        "sigma": 4,
        "sigma_V": 5,
        "gam_V": 0.9,
        "resid_ratio_true": 0.00109549,
        "resid_ratio_printed": 0.98005966
      }
    ],
    "pass_truth": true,
    "pass_power": true
  },
  "test_E": {
    "median_abs_bias": 0.00192748,
    "pass": true
  },
  "overall_pass": true
}
